wolfism8/__init__.py
wolfism8/ism8.py
python_wolfism8-1.4.1.dist-info/LICENSE
python_wolfism8-1.4.1.dist-info/METADATA
python_wolfism8-1.4.1.dist-info/WHEEL
python_wolfism8-1.4.1.dist-info/top_level.txt
python_wolfism8-1.4.1.dist-info/RECORD
